{
  "kind": "collectionType",
  "collectionName": "blogs",
  "info": {
    "singularName": "blog",
    "pluralName": "blogs",
    "displayName": "Blog",
    "description": ""
  },
  "options": {
    "draftAndPublish": true
  },
  "pluginOptions": {},
  "attributes": {
    "title": {
      "type": "string"
    },
    "date": {
      "type": "date"
    },
    "thumbnail": {
      "type": "media",
      "multiple": false,
      "required": false,
      "allowedTypes": [
        "images"
      ]
    },
    "text": {
      "type": "richtext"
    },
    "category": {
      "type": "enumeration",
      "enum": [
        "otomotif",
        "foto",
        "video"
      ]
    },
    "author": {
      "type": "string"
    },
    "slug": {
      "type": "uid",
      "targetField": "title"
    }
  }
}
